pysujanam-2.0.0.dist-info/licenses/LICENSE
sujanam/__init__.py
pysujanam-2.0.0.dist-info/METADATA
pysujanam-2.0.0.dist-info/WHEEL
pysujanam-2.0.0.dist-info/top_level.txt
pysujanam-2.0.0.dist-info/RECORD
